assignator/__init__.py
assignator/_cli.py
assignator/assignment.py
assignator-0.4.dist-info/LICENSE
assignator-0.4.dist-info/METADATA
assignator-0.4.dist-info/WHEEL
assignator-0.4.dist-info/entry_points.txt
assignator-0.4.dist-info/top_level.txt
assignator-0.4.dist-info/RECORD
