Metadata-Version: 2.1
Name: assignator
Version: 0.4
Summary: A tool assignate students to timeslots.
Home-page: https://github.com/jb-leger/assignator
Author: Jean-Benoist Leger
Author-email: jb@leger.tf
License: UNKNOWN
Keywords: csv
Platform: UNKNOWN
Classifier: Development Status :: 3 - Alpha
Classifier: License :: OSI Approved :: MIT License
Classifier: Programming Language :: Python :: 3 :: Only
Requires-Python: >=3.6
Requires-Dist: argparse
Requires-Dist: argcomplete
Requires-Dist: numpy
Requires-Dist: cchardet
